RL_Fundamentals/__init__.py
RL_Fundamentals/main.py
RL_Fundamentals-0.1.dist-info/METADATA
RL_Fundamentals-0.1.dist-info/WHEEL
RL_Fundamentals-0.1.dist-info/top_level.txt
RL_Fundamentals-0.1.dist-info/RECORD
