Metadata-Version: 2.1
Name: RL-Fundamentals
Version: 0.1
Requires-Dist: numpy >=1.11.1
